builder/__init__.py
builder/docker_builder.py
builder/docker_registry_auth.py
builder/docker_registry_operations.py
builder/docker_registry_publisher.py
cli/__init__.py
cli/geocicd.py
cli/interactive_cli.py
cli/interactive_cli_handlers.py
cli/interactive_cli_wizards.py
config/__init__.py
config/branch_matcher.py
config/environment_resolver.py
config/fst-defaults.yaml
config/geosystems-defaults.yaml
config/servers.yaml
config/examples/environment-specific-quality-gates.yaml
config/examples/geopipeline-config.yaml
config/examples/java-microservices.yaml
config/examples/monorepo.yaml
config/examples/simple-vue-app.yaml
deployer/__init__.py
deployer/argocd_generator.py
deployer/argocd_manifest_generator.py
deployer/argocd_repo_manager.py
deployer/kubernetes_deployer.py
deployer/kubernetes_resource_manager.py
generator/__init__.py
generator/gitlab_ci_deploy_builder.py
generator/gitlab_ci_generator.py
generator/gitlab_ci_jobs_builder.py
generator/gitlab_ci_quality_builder.py
generator/helm_chart_manager.py
generator/helm_generator.py
generator/helm_k8s_templates.py
generator/helm_template_generator.py
generator/helm_values_generator.py
parser/__init__.py
parser/config_defaults.py
parser/config_loader.py
parser/config_parser.py
parser/interpolator.py
parser/merger.py
parser/server_resolver.py
parser/validator.py
quality/__init__.py
quality/sonarqube_analyzer.py
quality/sonarqube_api_client.py
quality/sonarqube_parameter_builder.py
quality/sonarqube_quality_validator.py
schemas/ci-config.schema.json
utils/__init__.py
utils/artifact_metadata.py
utils/artifact_resolver.py
utils/artifact_tagger.py
utils/change_detection_helpers.py
utils/change_detector.py
utils/constants.py
utils/docker_registry_client.py
utils/dockerhub_registry_client.py
utils/ecr_registry_client.py
utils/exceptions.py
utils/exceptions_base.py
utils/exceptions_build.py
utils/exceptions_deploy.py
utils/git_branch_operations.py
utils/git_utils.py
utils/logging_config.py
utils/managed_file_generators.py
geocicd-1.0.4.dist-info/METADATA
geocicd-1.0.4.dist-info/WHEEL
geocicd-1.0.4.dist-info/entry_points.txt
geocicd-1.0.4.dist-info/top_level.txt
geocicd-1.0.4.dist-info/RECORD
