Metadata-Version: 2.4
Name: geocicd
Version: 1.0.4
Summary: Automated GitLab CI/CD pipeline generation from declarative configuration
Author: FST Team
Classifier: Development Status :: 4 - Beta
Classifier: Intended Audience :: Developers
Classifier: Programming Language :: Python :: 3
Classifier: Programming Language :: Python :: 3.11
Classifier: Programming Language :: Python :: 3.12
Requires-Python: >=3.11
Requires-Dist: PyYAML>=6.0.1
Requires-Dist: jsonschema>=4.19.0
Requires-Dist: GitPython>=3.1.40
Requires-Dist: requests>=2.31.0
Requires-Dist: click>=8.1.7
Requires-Dist: questionary>=2.0.1
Requires-Dist: rich>=13.7.0
Requires-Dist: typing-extensions>=4.8.0
Requires-Dist: packaging>=23.2
Provides-Extra: dev
Requires-Dist: hypothesis>=6.92.0; extra == "dev"
Requires-Dist: pytest>=7.4.3; extra == "dev"
Requires-Dist: pytest-cov>=4.1.0; extra == "dev"
